Metadata-Version: 2.2
Name: spedpy
Version: 1.2.3
Summary: Biblioteca para geração dos arquivos do Sistema Público de Escrituração Digital (SPED) para Python
Home-page: https://github.com/Trust-Code/python-sped
Author: Ismael Nascimento
Author-email: ismaelnjr@icloud.com.br
License: MIT License
Keywords: sped fiscal receita federal
Classifier: Programming Language :: Python :: 3
Classifier: License :: OSI Approved :: MIT License
Classifier: Operating System :: OS Independent
Requires-Python: >=3.6
License-File: LICENSE
Requires-Dist: coveralls==0.5
Requires-Dist: six==1.17.0
Requires-Dist: pytest==2.6.4
Dynamic: author
Dynamic: author-email
Dynamic: classifier
Dynamic: description
Dynamic: description-content-type
Dynamic: home-page
Dynamic: keywords
Dynamic: license
Dynamic: requires-dist
Dynamic: requires-python
Dynamic: summary
